turbopipe-1.2.3.dist-info/METADATA
turbopipe-1.2.3.dist-info/WHEEL
turbopipe/_turbopipe.cp39-win_amd64.pyd
turbopipe/_turbopipe.cp39-win_amd64.lib
turbopipe/__init__.py
turbopipe-1.2.3.dist-info/RECORD
