Metadata-Version: 2.4
Name: turbopipe
Version: 1.2.3
Summary: 🌀 Faster ModernGL Buffers inter-process data transfers for subprocesses
Author-Email: Tremeschin <29046864+Tremeschin@users.noreply.github.com>
License-Expression: MIT
Project-URL: GitHub, https://github.com/BrokenSource/TurboPipe
Project-URL: Changelog, https://brokensrc.dev/about/changelog
Project-URL: Funding, https://brokensrc.dev/about/sponsors
Project-URL: Contact, https://brokensrc.dev/about/contact
Project-URL: Homepage, https://brokensrc.dev
Requires-Python: >=3.7
Requires-Dist: moderngl
